setup.py
mtop/__init__.py
mtop/main.py
mtop.egg-info/PKG-INFO
mtop.egg-info/SOURCES.txt
mtop.egg-info/dependency_links.txt
mtop.egg-info/entry_points.txt
mtop.egg-info/not-zip-safe
mtop.egg-info/requires.txt
mtop.egg-info/top_level.txt
mtop/lib/__init__.py
mtop/lib/ops.py
mtop/lib/runner.py
mtop/lib/screen.py
mtop/lib/util.py