Metadata-Version: 1.0
Name: mtop
Version: 0.6
Summary: mtop is a top like tool for MongoDB.
Home-page: https://github.com/beaufour/mtop
Author: Allan Beaufour
Author-email: allan@beaufour.dk
License: UNKNOWN
Platform: UNKNOWN
